easychart/__init__.py
easychart/config.py
easychart/encoders.py
easychart/internals.py
easychart/ipynb.py
easychart/rendering.py
easychart/template.jinja
easychart/colormaps/__init__.py
easychart/colormaps/accent.json
easychart/colormaps/afmhot.json
easychart/colormaps/autumn.json
easychart/colormaps/binary.json
easychart/colormaps/blues.json
easychart/colormaps/bone.json
easychart/colormaps/brbg.json
easychart/colormaps/brg.json
easychart/colormaps/bugn.json
easychart/colormaps/bupu.json
easychart/colormaps/bwr.json
easychart/colormaps/cividis.json
easychart/colormaps/cmrmap.json
easychart/colormaps/cool.json
easychart/colormaps/coolwarm.json
easychart/colormaps/copper.json
easychart/colormaps/cubehelix.json
easychart/colormaps/dark2.json
easychart/colormaps/flag.json
easychart/colormaps/gist_earth.json
easychart/colormaps/gist_gray.json
easychart/colormaps/gist_heat.json
easychart/colormaps/gist_ncar.json
easychart/colormaps/gist_rainbow.json
easychart/colormaps/gist_stern.json
easychart/colormaps/gist_yarg.json
easychart/colormaps/gnbu.json
easychart/colormaps/gnuplot.json
easychart/colormaps/gnuplot2.json
easychart/colormaps/gray.json
easychart/colormaps/greens.json
easychart/colormaps/greys.json
easychart/colormaps/hot.json
easychart/colormaps/hsv.json
easychart/colormaps/inferno.json
easychart/colormaps/jet.json
easychart/colormaps/magma.json
easychart/colormaps/nipy_spectral.json
easychart/colormaps/ocean.json
easychart/colormaps/oranges.json
easychart/colormaps/orrd.json
easychart/colormaps/paired.json
easychart/colormaps/pastel1.json
easychart/colormaps/pastel2.json
easychart/colormaps/pink.json
easychart/colormaps/piyg.json
easychart/colormaps/plasma.json
easychart/colormaps/prgn.json
easychart/colormaps/prism.json
easychart/colormaps/pubu.json
easychart/colormaps/pubugn.json
easychart/colormaps/puor.json
easychart/colormaps/purd.json
easychart/colormaps/purples.json
easychart/colormaps/rainbow.json
easychart/colormaps/rdbu.json
easychart-0.1.31.dist-info/LICENSE
easychart-0.1.31.dist-info/METADATA
easychart-0.1.31.dist-info/WHEEL
easychart-0.1.31.dist-info/top_level.txt
easychart-0.1.31.dist-info/RECORD
