Metadata-Version: 2.1
Name: easychart
Version: 0.1.31
Summary: Highcharts meets python in your Jupyter notebook
Home-page: https://easychart.readthedocs.io/en/latest/
Author: david.schenck@outlook.com
Author-email: david.schenck@outlook.com
Classifier: Programming Language :: Python :: 3
Classifier: License :: OSI Approved :: MIT License
Classifier: Operating System :: OS Independent
License-File: LICENSE
Requires-Dist: pandas
Requires-Dist: numpy
Requires-Dist: easytree>=0.2.3
Requires-Dist: simplejson
Requires-Dist: jinja2
Requires-Dist: requests
Requires-Dist: ipython
